{
  "version":"1.3.15",
  "params":{
    "model":"vmaf_v0.6.1.pkl",
    "scaledWidth":768,
    "scaledHeight":432,
    "subsample":1,
    "num_bootstrap_models":0,
    "bootstrap_model_list_str":"",
    "pool":"mean"
  },
  "metrics":[
    "adm2",
    "motion2",
    "ms_ssim",
    "psnr",
    "ssim",
    "vif_scale0",
    "vif_scale1",
    "vif_scale2",
    "vif_scale3",
    "vmaf"
  ],
  "frames":[
    {
      "frameNum":0,
      "metrics":{
        "adm2":0.89983,
        "motion2":0.0,
        "ms_ssim":0.95477,
        "psnr":34.05881,
        "ssim":0.9178500000000001,
        "vif_scale0":0.34751,
        "vif_scale1":0.72016,
        "vif_scale2":0.8323700000000001,
        "vif_scale3":0.89471,
        "vmaf":63.00867
      }
    },
    {
      "frameNum":1,
      "metrics":{
        "adm2":0.89772,
        "motion2":4.9764,
        "ms_ssim":0.95378,
        "psnr":34.0714,
        "ssim":0.91856,
        "vif_scale0":0.34866,
        "vif_scale1":0.70873,
        "vif_scale2":0.82129,
        "vif_scale3":0.88692,
        "vmaf":67.11099
      }
    },
    {
      "frameNum":2,
      "metrics":{
        "adm2":0.91422,
        "motion2":4.94874,
        "ms_ssim":0.9652500000000001,
        "psnr":35.18671,
        "ssim":0.93724,
        "vif_scale0":0.39977,
        "vif_scale1":0.77173,
        "vif_scale2":0.86724,
        "vif_scale3":0.9196800000000001,
        "vmaf":73.90506999999999
      }
    },
    {
      "frameNum":3,
      "metrics":{
        "adm2":0.92687,
        "motion2":4.8859,
        "ms_ssim":0.97237,
        "psnr":36.03917,
        "ssim":0.94991,
        "vif_scale0":0.43755,
        "vif_scale1":0.81295,
        "vif_scale2":0.89477,
        "vif_scale3":0.9375,
        "vmaf":78.59741
      }
    },
    {
      "frameNum":4,
      "metrics":{
        "adm2":0.93519,
        "motion2":4.80029,
        "ms_ssim":0.97683,
        "psnr":36.65334,
        "ssim":0.95726,
        "vif_scale0":0.46599,
        "vif_scale1":0.8412500000000001,
        "vif_scale2":0.91264,
        "vif_scale3":0.94762,
        "vmaf":81.61076
      }
    },
    {
      "frameNum":5,
      "metrics":{
        "adm2":0.94292,
        "motion2":4.80029,
        "ms_ssim":0.9805199999999999,
        "psnr":37.27812,
        "ssim":0.9638600000000001,
        "vif_scale0":0.49384,
        "vif_scale1":0.86452,
        "vif_scale2":0.92674,
        "vif_scale3":0.95585,
        "vmaf":84.38285999999999
      }
    },
    {
      "frameNum":6,
      "metrics":{
        "adm2":0.94789,
        "motion2":4.63803,
        "ms_ssim":0.98249,
        "psnr":37.68167,
        "ssim":0.96756,
        "vif_scale0":0.51198,
        "vif_scale1":0.88008,
        "vif_scale2":0.93634,
        "vif_scale3":0.96233,
        "vmaf":86.1264
      }
    },
    {
      "frameNum":7,
      "metrics":{
        "adm2":0.95001,
        "motion2":4.63803,
        "ms_ssim":0.98367,
        "psnr":37.90598,
        "ssim":0.96965,
        "vif_scale0":0.5235,
        "vif_scale1":0.89118,
        "vif_scale2":0.94287,
        "vif_scale3":0.96617,
        "vmaf":87.142
      }
    },
    {
      "frameNum":8,
      "metrics":{
        "adm2":0.95214,
        "motion2":4.6519,
        "ms_ssim":0.9848,
        "psnr":37.93844,
        "ssim":0.97209,
        "vif_scale0":0.53594,
        "vif_scale1":0.89689,
        "vif_scale2":0.94521,
        "vif_scale3":0.96705,
        "vmaf":87.76981000000001
      }
    },
    {
      "frameNum":9,
      "metrics":{
        "adm2":0.95296,
        "motion2":4.63544,
        "ms_ssim":0.98583,
        "psnr":38.2052,
        "ssim":0.97381,
        "vif_scale0":0.54719,
        "vif_scale1":0.9039,
        "vif_scale2":0.94935,
        "vif_scale3":0.96953,
        "vmaf":88.29322000000001
      }
    },
    {
      "frameNum":10,
      "metrics":{
        "adm2":0.95494,
        "motion2":4.59315,
        "ms_ssim":0.9867,
        "psnr":38.45787,
        "ssim":0.97562,
        "vif_scale0":0.55989,
        "vif_scale1":0.9101399999999999,
        "vif_scale2":0.9529,
        "vif_scale3":0.97168,
        "vmaf":88.98309
      }
    },
    {
      "frameNum":11,
      "metrics":{
        "adm2":0.9573700000000001,
        "motion2":4.52507,
        "ms_ssim":0.98734,
        "psnr":38.62613,
        "ssim":0.97663,
        "vif_scale0":0.5668800000000001,
        "vif_scale1":0.91433,
        "vif_scale2":0.9548,
        "vif_scale3":0.97233,
        "vmaf":89.55824
      }
    },
    {
      "frameNum":12,
      "metrics":{
        "adm2":0.95748,
        "motion2":4.52507,
        "ms_ssim":0.98785,
        "psnr":38.73402,
        "ssim":0.97764,
        "vif_scale0":0.57341,
        "vif_scale1":0.91887,
        "vif_scale2":0.95735,
        "vif_scale3":0.97301,
        "vmaf":89.74679999999999
      }
    },
    {
      "frameNum":13,
      "metrics":{
        "adm2":0.9607599999999999,
        "motion2":4.52636,
        "ms_ssim":0.98843,
        "psnr":38.92632,
        "ssim":0.97871,
        "vif_scale0":0.5823700000000001,
        "vif_scale1":0.92228,
        "vif_scale2":0.95897,
        "vif_scale3":0.97433,
        "vmaf":90.62743
      }
    },
    {
      "frameNum":14,
      "metrics":{
        "adm2":0.96189,
        "motion2":4.48383,
        "ms_ssim":0.98863,
        "psnr":38.99789,
        "ssim":0.97919,
        "vif_scale0":0.58577,
        "vif_scale1":0.92255,
        "vif_scale2":0.9585399999999999,
        "vif_scale3":0.97399,
        "vmaf":90.77333
      }
    },
    {
      "frameNum":15,
      "metrics":{
        "adm2":0.96318,
        "motion2":4.43921,
        "ms_ssim":0.98913,
        "psnr":39.14418,
        "ssim":0.98015,
        "vif_scale0":0.5925,
        "vif_scale1":0.92531,
        "vif_scale2":0.95975,
        "vif_scale3":0.97521,
        "vmaf":91.14651000000001
      }
    },
    {
      "frameNum":16,
      "metrics":{
        "adm2":0.96199,
        "motion2":4.4293,
        "ms_ssim":0.98927,
        "psnr":39.15317,
        "ssim":0.98024,
        "vif_scale0":0.59288,
        "vif_scale1":0.92646,
        "vif_scale2":0.96056,
        "vif_scale3":0.97529,
        "vmaf":90.92225999999999
      }
    },
    {
      "frameNum":17,
      "metrics":{
        "adm2":0.96249,
        "motion2":4.37473,
        "ms_ssim":0.98955,
        "psnr":39.2841,
        "ssim":0.98099,
        "vif_scale0":0.5988,
        "vif_scale1":0.92821,
        "vif_scale2":0.96144,
        "vif_scale3":0.97523,
        "vmaf":90.99759
      }
    },
    {
      "frameNum":18,
      "metrics":{
        "adm2":0.96187,
        "motion2":4.31601,
        "ms_ssim":0.98967,
        "psnr":39.30186,
        "ssim":0.98128,
        "vif_scale0":0.59904,
        "vif_scale1":0.92982,
        "vif_scale2":0.96246,
        "vif_scale3":0.9764,
        "vmaf":90.93501000000001
      }
    },
    {
      "frameNum":19,
      "metrics":{
        "adm2":0.96372,
        "motion2":4.27129,
        "ms_ssim":0.99,
        "psnr":39.39724,
        "ssim":0.98185,
        "vif_scale0":0.60382,
        "vif_scale1":0.93103,
        "vif_scale2":0.96333,
        "vif_scale3":0.9767400000000001,
        "vmaf":91.34515
      }
    },
    {
      "frameNum":20,
      "metrics":{
        "adm2":0.96294,
        "motion2":4.18608,
        "ms_ssim":0.98994,
        "psnr":39.31968,
        "ssim":0.98178,
        "vif_scale0":0.60123,
        "vif_scale1":0.9301199999999999,
        "vif_scale2":0.96193,
        "vif_scale3":0.975,
        "vmaf":90.87415
      }
    },
    {
      "frameNum":21,
      "metrics":{
        "adm2":0.96235,
        "motion2":4.0901,
        "ms_ssim":0.98992,
        "psnr":39.29375,
        "ssim":0.98177,
        "vif_scale0":0.59982,
        "vif_scale1":0.92991,
        "vif_scale2":0.9618,
        "vif_scale3":0.97496,
        "vmaf":90.62419
      }
    },
    {
      "frameNum":22,
      "metrics":{
        "adm2":0.96413,
        "motion2":4.0901,
        "ms_ssim":0.99008,
        "psnr":39.38138,
        "ssim":0.982,
        "vif_scale0":0.60258,
        "vif_scale1":0.92938,
        "vif_scale2":0.96189,
        "vif_scale3":0.97558,
        "vmaf":91.05816
      }
    },
    {
      "frameNum":23,
      "metrics":{
        "adm2":0.96624,
        "motion2":4.13253,
        "ms_ssim":0.99022,
        "psnr":39.41464,
        "ssim":0.98226,
        "vif_scale0":0.60475,
        "vif_scale1":0.9309500000000001,
        "vif_scale2":0.96278,
        "vif_scale3":0.97662,
        "vmaf":91.68785
      }
    },
    {
      "frameNum":24,
      "metrics":{
        "adm2":0.96843,
        "motion2":4.11056,
        "ms_ssim":0.99044,
        "psnr":39.50939,
        "ssim":0.98273,
        "vif_scale0":0.60897,
        "vif_scale1":0.93262,
        "vif_scale2":0.96394,
        "vif_scale3":0.97767,
        "vmaf":92.26759
      }
    },
    {
      "frameNum":25,
      "metrics":{
        "adm2":0.96692,
        "motion2":4.0539,
        "ms_ssim":0.99032,
        "psnr":39.46548,
        "ssim":0.98241,
        "vif_scale0":0.60661,
        "vif_scale1":0.93194,
        "vif_scale2":0.96311,
        "vif_scale3":0.97671,
        "vmaf":91.7624
      }
    },
    {
      "frameNum":26,
      "metrics":{
        "adm2":0.96753,
        "motion2":3.94746,
        "ms_ssim":0.99026,
        "psnr":39.43524,
        "ssim":0.9824000000000001,
        "vif_scale0":0.6061299999999999,
        "vif_scale1":0.9317,
        "vif_scale2":0.9628,
        "vif_scale3":0.97559,
        "vmaf":91.66373
      }
    },
    {
      "frameNum":27,
      "metrics":{
        "adm2":0.96667,
        "motion2":3.87231,
        "ms_ssim":0.99028,
        "psnr":39.36949,
        "ssim":0.98234,
        "vif_scale0":0.60245,
        "vif_scale1":0.9313399999999999,
        "vif_scale2":0.96304,
        "vif_scale3":0.97703,
        "vmaf":91.51251999999999
      }
    },
    {
      "frameNum":28,
      "metrics":{
        "adm2":0.96644,
        "motion2":3.82666,
        "ms_ssim":0.99046,
        "psnr":39.44873,
        "ssim":0.98273,
        "vif_scale0":0.60603,
        "vif_scale1":0.93284,
        "vif_scale2":0.96391,
        "vif_scale3":0.9772,
        "vmaf":91.4598
      }
    },
    {
      "frameNum":29,
      "metrics":{
        "adm2":0.96807,
        "motion2":3.82243,
        "ms_ssim":0.99022,
        "psnr":39.35253,
        "ssim":0.9823499999999999,
        "vif_scale0":0.60188,
        "vif_scale1":0.93201,
        "vif_scale2":0.96383,
        "vif_scale3":0.97715,
        "vmaf":91.80027
      }
    },
    {
      "frameNum":30,
      "metrics":{
        "adm2":0.968,
        "motion2":3.82243,
        "ms_ssim":0.99054,
        "psnr":39.49411,
        "ssim":0.98293,
        "vif_scale0":0.6068,
        "vif_scale1":0.93318,
        "vif_scale2":0.9642500000000001,
        "vif_scale3":0.97775,
        "vmaf":91.85104
      }
    },
    {
      "frameNum":31,
      "metrics":{
        "adm2":0.96731,
        "motion2":3.82369,
        "ms_ssim":0.99052,
        "psnr":39.49101,
        "ssim":0.98298,
        "vif_scale0":0.6065199999999999,
        "vif_scale1":0.93293,
        "vif_scale2":0.96409,
        "vif_scale3":0.9764699999999999,
        "vmaf":91.59384
      }
    },
    {
      "frameNum":32,
      "metrics":{
        "adm2":0.9638099999999999,
        "motion2":3.82369,
        "ms_ssim":0.98934,
        "psnr":38.60619,
        "ssim":0.98082,
        "vif_scale0":0.59149,
        "vif_scale1":0.91999,
        "vif_scale2":0.95491,
        "vif_scale3":0.97015,
        "vmaf":89.92825000000001
      }
    },
    {
      "frameNum":33,
      "metrics":{
        "adm2":0.96382,
        "motion2":3.89251,
        "ms_ssim":0.98932,
        "psnr":38.66896,
        "ssim":0.98065,
        "vif_scale0":0.59449,
        "vif_scale1":0.92009,
        "vif_scale2":0.95494,
        "vif_scale3":0.97109,
        "vmaf":90.08629000000001
      }
    },
    {
      "frameNum":34,
      "metrics":{
        "adm2":0.95924,
        "motion2":3.93561,
        "ms_ssim":0.98769,
        "psnr":37.42048,
        "ssim":0.97798,
        "vif_scale0":0.57633,
        "vif_scale1":0.9049700000000001,
        "vif_scale2":0.94304,
        "vif_scale3":0.95968,
        "vmaf":87.74289
      }
    },
    {
      "frameNum":35,
      "metrics":{
        "adm2":0.9593699999999999,
        "motion2":3.88623,
        "ms_ssim":0.98731,
        "psnr":37.42237,
        "ssim":0.97709,
        "vif_scale0":0.5734,
        "vif_scale1":0.90189,
        "vif_scale2":0.94143,
        "vif_scale3":0.96082,
        "vmaf":87.73448999999999
      }
    },
    {
      "frameNum":36,
      "metrics":{
        "adm2":0.95716,
        "motion2":3.7827,
        "ms_ssim":0.98668,
        "psnr":37.29933,
        "ssim":0.9762,
        "vif_scale0":0.56649,
        "vif_scale1":0.89789,
        "vif_scale2":0.93807,
        "vif_scale3":0.95914,
        "vmaf":86.86803
      }
    },
    {
      "frameNum":37,
      "metrics":{
        "adm2":0.95738,
        "motion2":3.7827,
        "ms_ssim":0.9866200000000001,
        "psnr":37.31134,
        "ssim":0.97597,
        "vif_scale0":0.56753,
        "vif_scale1":0.89834,
        "vif_scale2":0.93803,
        "vif_scale3":0.95877,
        "vmaf":86.88323
      }
    },
    {
      "frameNum":38,
      "metrics":{
        "adm2":0.95824,
        "motion2":3.7999,
        "ms_ssim":0.98655,
        "psnr":37.26636,
        "ssim":0.97576,
        "vif_scale0":0.56651,
        "vif_scale1":0.8972599999999999,
        "vif_scale2":0.93808,
        "vif_scale3":0.95802,
        "vmaf":87.03273
      }
    },
    {
      "frameNum":39,
      "metrics":{
        "adm2":0.96109,
        "motion2":3.76821,
        "ms_ssim":0.98636,
        "psnr":37.21854,
        "ssim":0.97579,
        "vif_scale0":0.56655,
        "vif_scale1":0.8978699999999999,
        "vif_scale2":0.93846,
        "vif_scale3":0.95821,
        "vmaf":87.63630999999999
      }
    },
    {
      "frameNum":40,
      "metrics":{
        "adm2":0.9614200000000001,
        "motion2":3.68033,
        "ms_ssim":0.98627,
        "psnr":37.17302,
        "ssim":0.97542,
        "vif_scale0":0.56707,
        "vif_scale1":0.89696,
        "vif_scale2":0.93659,
        "vif_scale3":0.95567,
        "vmaf":87.32371999999999
      }
    },
    {
      "frameNum":41,
      "metrics":{
        "adm2":0.96063,
        "motion2":3.59202,
        "ms_ssim":0.98589,
        "psnr":37.0563,
        "ssim":0.97502,
        "vif_scale0":0.56181,
        "vif_scale1":0.89429,
        "vif_scale2":0.93475,
        "vif_scale3":0.95338,
        "vmaf":86.79783999999999
      }
    },
    {
      "frameNum":42,
      "metrics":{
        "adm2":0.9592000000000001,
        "motion2":3.59202,
        "ms_ssim":0.98578,
        "psnr":37.02124,
        "ssim":0.97487,
        "vif_scale0":0.5605,
        "vif_scale1":0.89371,
        "vif_scale2":0.9336,
        "vif_scale3":0.9518,
        "vmaf":86.32181
      }
    },
    {
      "frameNum":43,
      "metrics":{
        "adm2":0.95819,
        "motion2":3.48999,
        "ms_ssim":0.98563,
        "psnr":36.98141,
        "ssim":0.97485,
        "vif_scale0":0.55992,
        "vif_scale1":0.89209,
        "vif_scale2":0.93175,
        "vif_scale3":0.94964,
        "vmaf":85.73862
      }
    },
    {
      "frameNum":44,
      "metrics":{
        "adm2":0.95877,
        "motion2":3.48999,
        "ms_ssim":0.9855,
        "psnr":36.9071,
        "ssim":0.9746899999999999,
        "vif_scale0":0.55996,
        "vif_scale1":0.89173,
        "vif_scale2":0.93101,
        "vif_scale3":0.94892,
        "vmaf":85.77633
      }
    },
    {
      "frameNum":45,
      "metrics":{
        "adm2":0.95849,
        "motion2":3.52284,
        "ms_ssim":0.98551,
        "psnr":36.90829,
        "ssim":0.97479,
        "vif_scale0":0.56255,
        "vif_scale1":0.89154,
        "vif_scale2":0.93016,
        "vif_scale3":0.94807,
        "vmaf":85.65097
      }
    },
    {
      "frameNum":46,
      "metrics":{
        "adm2":0.95762,
        "motion2":3.47631,
        "ms_ssim":0.98525,
        "psnr":36.80261,
        "ssim":0.97435,
        "vif_scale0":0.55777,
        "vif_scale1":0.8905999999999999,
        "vif_scale2":0.92952,
        "vif_scale3":0.94735,
        "vmaf":85.3319
      }
    },
    {
      "frameNum":47,
      "metrics":{
        "adm2":0.95668,
        "motion2":3.42558,
        "ms_ssim":0.9852,
        "psnr":36.81015,
        "ssim":0.97455,
        "vif_scale0":0.56038,
        "vif_scale1":0.891,
        "vif_scale2":0.9293,
        "vif_scale3":0.94706,
        "vmaf":85.03742
      }
    },
    {
      "frameNum":48,
      "metrics":{
        "adm2":0.95692,
        "motion2":3.38226,
        "ms_ssim":0.98507,
        "psnr":36.72487,
        "ssim":0.97409,
        "vif_scale0":0.55676,
        "vif_scale1":0.89027,
        "vif_scale2":0.92893,
        "vif_scale3":0.94689,
        "vmaf":85.01102
      }
    },
    {
      "frameNum":49,
      "metrics":{
        "adm2":0.9549299999999999,
        "motion2":3.34626,
        "ms_ssim":0.98497,
        "psnr":36.69876,
        "ssim":0.97409,
        "vif_scale0":0.55686,
        "vif_scale1":0.89019,
        "vif_scale2":0.92827,
        "vif_scale3":0.94495,
        "vmaf":84.36729
      }
    },
    {
      "frameNum":50,
      "metrics":{
        "adm2":0.95714,
        "motion2":3.27665,
        "ms_ssim":0.98502,
        "psnr":36.78437,
        "ssim":0.97445,
        "vif_scale0":0.55943,
        "vif_scale1":0.89134,
        "vif_scale2":0.92808,
        "vif_scale3":0.94584,
        "vmaf":84.81353
      }
    },
    {
      "frameNum":51,
      "metrics":{
        "adm2":0.95795,
        "motion2":3.26682,
        "ms_ssim":0.98463,
        "psnr":36.71817,
        "ssim":0.97393,
        "vif_scale0":0.55355,
        "vif_scale1":0.88778,
        "vif_scale2":0.92575,
        "vif_scale3":0.94453,
        "vmaf":84.7829
      }
    },
    {
      "frameNum":52,
      "metrics":{
        "adm2":0.95745,
        "motion2":3.26682,
        "ms_ssim":0.9847,
        "psnr":36.77424,
        "ssim":0.9742,
        "vif_scale0":0.55826,
        "vif_scale1":0.88872,
        "vif_scale2":0.92588,
        "vif_scale3":0.94298,
        "vmaf":84.55414
      }
    },
    {
      "frameNum":53,
      "metrics":{
        "adm2":0.95926,
        "motion2":3.32428,
        "ms_ssim":0.9846200000000001,
        "psnr":36.78244,
        "ssim":0.97427,
        "vif_scale0":0.55743,
        "vif_scale1":0.88707,
        "vif_scale2":0.92421,
        "vif_scale3":0.9416099999999999,
        "vmaf":84.83562000000001
      }
    },
    {
      "frameNum":54,
      "metrics":{
        "adm2":0.95846,
        "motion2":3.25314,
        "ms_ssim":0.98455,
        "psnr":36.78989,
        "ssim":0.97415,
        "vif_scale0":0.55625,
        "vif_scale1":0.88767,
        "vif_scale2":0.92461,
        "vif_scale3":0.94249,
        "vmaf":84.66631
      }
    },
    {
      "frameNum":55,
      "metrics":{
        "adm2":0.95589,
        "motion2":3.21709,
        "ms_ssim":0.98427,
        "psnr":36.75611,
        "ssim":0.97375,
        "vif_scale0":0.55313,
        "vif_scale1":0.88609,
        "vif_scale2":0.92359,
        "vif_scale3":0.94073,
        "vmaf":83.90047
      }
    },
    {
      "frameNum":56,
      "metrics":{
        "adm2":0.95583,
        "motion2":3.15368,
        "ms_ssim":0.98419,
        "psnr":36.76516,
        "ssim":0.97389,
        "vif_scale0":0.5528999999999999,
        "vif_scale1":0.8865499999999999,
        "vif_scale2":0.92401,
        "vif_scale3":0.94175,
        "vmaf":83.91031
      }
    },
    {
      "frameNum":57,
      "metrics":{
        "adm2":0.95512,
        "motion2":3.13376,
        "ms_ssim":0.98415,
        "psnr":36.73446,
        "ssim":0.97355,
        "vif_scale0":0.55086,
        "vif_scale1":0.88607,
        "vif_scale2":0.92317,
        "vif_scale3":0.94148,
        "vmaf":83.68214
      }
    },
    {
      "frameNum":58,
      "metrics":{
        "adm2":0.95435,
        "motion2":3.07143,
        "ms_ssim":0.9840100000000001,
        "psnr":36.74828,
        "ssim":0.9736399999999999,
        "vif_scale0":0.551,
        "vif_scale1":0.8864300000000001,
        "vif_scale2":0.92361,
        "vif_scale3":0.94062,
        "vmaf":83.39485999999999
      }
    },
    {
      "frameNum":59,
      "metrics":{
        "adm2":0.95592,
        "motion2":3.07143,
        "ms_ssim":0.98387,
        "psnr":36.74591,
        "ssim":0.97366,
        "vif_scale0":0.55033,
        "vif_scale1":0.88493,
        "vif_scale2":0.92221,
        "vif_scale3":0.94063,
        "vmaf":83.67337999999999
      }
    },
    {
      "frameNum":60,
      "metrics":{
        "adm2":0.95491,
        "motion2":3.08076,
        "ms_ssim":0.98375,
        "psnr":36.70352,
        "ssim":0.97363,
        "vif_scale0":0.5486799999999999,
        "vif_scale1":0.88425,
        "vif_scale2":0.92215,
        "vif_scale3":0.9403,
        "vmaf":83.44376
      }
    },
    {
      "frameNum":61,
      "metrics":{
        "adm2":0.95567,
        "motion2":3.07903,
        "ms_ssim":0.98362,
        "psnr":36.72644,
        "ssim":0.9737,
        "vif_scale0":0.54924,
        "vif_scale1":0.88474,
        "vif_scale2":0.92263,
        "vif_scale3":0.94025,
        "vmaf":83.61971
      }
    },
    {
      "frameNum":62,
      "metrics":{
        "adm2":0.95779,
        "motion2":3.00259,
        "ms_ssim":0.98341,
        "psnr":36.70668,
        "ssim":0.97336,
        "vif_scale0":0.54645,
        "vif_scale1":0.8841599999999999,
        "vif_scale2":0.92197,
        "vif_scale3":0.93977,
        "vmaf":83.91914
      }
    },
    {
      "frameNum":63,
      "metrics":{
        "adm2":0.95873,
        "motion2":2.93469,
        "ms_ssim":0.98336,
        "psnr":36.70078,
        "ssim":0.97334,
        "vif_scale0":0.5457,
        "vif_scale1":0.88401,
        "vif_scale2":0.92208,
        "vif_scale3":0.9402700000000001,
        "vmaf":84.08293
      }
    },
    {
      "frameNum":64,
      "metrics":{
        "adm2":0.95813,
        "motion2":2.87552,
        "ms_ssim":0.98324,
        "psnr":36.69239,
        "ssim":0.97322,
        "vif_scale0":0.5434600000000001,
        "vif_scale1":0.8832,
        "vif_scale2":0.9214599999999999,
        "vif_scale3":0.9388,
        "vmaf":83.74844
      }
    },
    {
      "frameNum":65,
      "metrics":{
        "adm2":0.96113,
        "motion2":2.87552,
        "ms_ssim":0.98353,
        "psnr":36.7632,
        "ssim":0.97366,
        "vif_scale0":0.54723,
        "vif_scale1":0.88534,
        "vif_scale2":0.92275,
        "vif_scale3":0.93933,
        "vmaf":84.47566
      }
    },
    {
      "frameNum":66,
      "metrics":{
        "adm2":0.95389,
        "motion2":2.81346,
        "ms_ssim":0.98143,
        "psnr":36.27442,
        "ssim":0.97026,
        "vif_scale0":0.5278,
        "vif_scale1":0.87544,
        "vif_scale2":0.9174099999999999,
        "vif_scale3":0.93664,
        "vmaf":82.46886000000001
      }
    },
    {
      "frameNum":67,
      "metrics":{
        "adm2":0.9539299999999999,
        "motion2":2.81346,
        "ms_ssim":0.98145,
        "psnr":36.30058,
        "ssim":0.97013,
        "vif_scale0":0.52789,
        "vif_scale1":0.87523,
        "vif_scale2":0.91767,
        "vif_scale3":0.93819,
        "vmaf":82.60729000000001
      }
    },
    {
      "frameNum":68,
      "metrics":{
        "adm2":0.95307,
        "motion2":2.91595,
        "ms_ssim":0.98144,
        "psnr":36.3559,
        "ssim":0.97024,
        "vif_scale0":0.53048,
        "vif_scale1":0.87604,
        "vif_scale2":0.9182399999999999,
        "vif_scale3":0.93911,
        "vmaf":82.63672
      }
    },
    {
      "frameNum":69,
      "metrics":{
        "adm2":0.95486,
        "motion2":2.91946,
        "ms_ssim":0.98149,
        "psnr":36.35586,
        "ssim":0.97038,
        "vif_scale0":0.52813,
        "vif_scale1":0.8757200000000001,
        "vif_scale2":0.91808,
        "vif_scale3":0.93875,
        "vmaf":82.98912
      }
    },
    {
      "frameNum":70,
      "metrics":{
        "adm2":0.95564,
        "motion2":2.93531,
        "ms_ssim":0.98159,
        "psnr":36.40817,
        "ssim":0.97052,
        "vif_scale0":0.53145,
        "vif_scale1":0.87738,
        "vif_scale2":0.919,
        "vif_scale3":0.93919,
        "vmaf":83.23887999999999
      }
    },
    {
      "frameNum":71,
      "metrics":{
        "adm2":0.95784,
        "motion2":2.91673,
        "ms_ssim":0.9815199999999999,
        "psnr":36.41215,
        "ssim":0.97053,
        "vif_scale0":0.5301399999999999,
        "vif_scale1":0.87668,
        "vif_scale2":0.91892,
        "vif_scale3":0.93965,
        "vmaf":83.72031
      }
    },
    {
      "frameNum":72,
      "metrics":{
        "adm2":0.95556,
        "motion2":2.91673,
        "ms_ssim":0.98142,
        "psnr":36.3805,
        "ssim":0.9702499999999999,
        "vif_scale0":0.52782,
        "vif_scale1":0.8767200000000001,
        "vif_scale2":0.91881,
        "vif_scale3":0.93925,
        "vmaf":83.20513
      }
    },
    {
      "frameNum":73,
      "metrics":{
        "adm2":0.9550999999999999,
        "motion2":2.96651,
        "ms_ssim":0.9816,
        "psnr":36.45315,
        "ssim":0.97084,
        "vif_scale0":0.53099,
        "vif_scale1":0.87771,
        "vif_scale2":0.92,
        "vif_scale3":0.9394400000000001,
        "vmaf":83.22351
      }
    },
    {
      "frameNum":74,
      "metrics":{
        "adm2":0.95291,
        "motion2":2.86499,
        "ms_ssim":0.97988,
        "psnr":35.71838,
        "ssim":0.96788,
        "vif_scale0":0.51071,
        "vif_scale1":0.86245,
        "vif_scale2":0.91053,
        "vif_scale3":0.93529,
        "vmaf":81.97718999999999
      }
    },
    {
      "frameNum":75,
      "metrics":{
        "adm2":0.95304,
        "motion2":2.86499,
        "ms_ssim":0.97962,
        "psnr":35.59095,
        "ssim":0.96722,
        "vif_scale0":0.50705,
        "vif_scale1":0.85904,
        "vif_scale2":0.9077,
        "vif_scale3":0.93404,
        "vmaf":81.80606
      }
    },
    {
      "frameNum":76,
      "metrics":{
        "adm2":0.95406,
        "motion2":2.93779,
        "ms_ssim":0.97941,
        "psnr":35.56475,
        "ssim":0.96713,
        "vif_scale0":0.50695,
        "vif_scale1":0.85783,
        "vif_scale2":0.90647,
        "vif_scale3":0.93296,
        "vmaf":81.97644
      }
    },
    {
      "frameNum":77,
      "metrics":{
        "adm2":0.95219,
        "motion2":2.93779,
        "ms_ssim":0.97942,
        "psnr":35.53639,
        "ssim":0.96721,
        "vif_scale0":0.5059,
        "vif_scale1":0.85544,
        "vif_scale2":0.90361,
        "vif_scale3":0.92985,
        "vmaf":81.23352
      }
    },
    {
      "frameNum":78,
      "metrics":{
        "adm2":0.95395,
        "motion2":2.95666,
        "ms_ssim":0.97931,
        "psnr":35.53403,
        "ssim":0.96645,
        "vif_scale0":0.5047199999999999,
        "vif_scale1":0.85562,
        "vif_scale2":0.90377,
        "vif_scale3":0.9301,
        "vmaf":81.6558
      }
    },
    {
      "frameNum":79,
      "metrics":{
        "adm2":0.95158,
        "motion2":2.94825,
        "ms_ssim":0.97917,
        "psnr":35.5638,
        "ssim":0.9664700000000001,
        "vif_scale0":0.50536,
        "vif_scale1":0.8557399999999999,
        "vif_scale2":0.90268,
        "vif_scale3":0.92926,
        "vmaf":81.03479
      }
    },
    {
      "frameNum":80,
      "metrics":{
        "adm2":0.95128,
        "motion2":2.94825,
        "ms_ssim":0.97902,
        "psnr":35.51555,
        "ssim":0.96623,
        "vif_scale0":0.5043,
        "vif_scale1":0.8555700000000001,
        "vif_scale2":0.90256,
        "vif_scale3":0.92587,
        "vmaf":80.71057
      }
    },
    {
      "frameNum":81,
      "metrics":{
        "adm2":0.94845,
        "motion2":2.94972,
        "ms_ssim":0.97902,
        "psnr":35.51152,
        "ssim":0.966,
        "vif_scale0":0.50506,
        "vif_scale1":0.85467,
        "vif_scale2":0.901,
        "vif_scale3":0.92619,
        "vmaf":80.07598
      }
    },
    {
      "frameNum":82,
      "metrics":{
        "adm2":0.95387,
        "motion2":2.87149,
        "ms_ssim":0.97892,
        "psnr":35.45386,
        "ssim":0.96627,
        "vif_scale0":0.50293,
        "vif_scale1":0.85399,
        "vif_scale2":0.90072,
        "vif_scale3":0.92598,
        "vmaf":81.10795
      }
    },
    {
      "frameNum":83,
      "metrics":{
        "adm2":0.94967,
        "motion2":2.87149,
        "ms_ssim":0.97882,
        "psnr":35.44964,
        "ssim":0.96638,
        "vif_scale0":0.50274,
        "vif_scale1":0.85419,
        "vif_scale2":0.9003100000000001,
        "vif_scale3":0.92315,
        "vmaf":79.98874000000001
      }
    },
    {
      "frameNum":84,
      "metrics":{
        "adm2":0.95063,
        "motion2":2.89882,
        "ms_ssim":0.9785,
        "psnr":35.36265,
        "ssim":0.96571,
        "vif_scale0":0.50062,
        "vif_scale1":0.85163,
        "vif_scale2":0.8999200000000001,
        "vif_scale3":0.9241200000000001,
        "vmaf":80.29009000000001
      }
    },
    {
      "frameNum":85,
      "metrics":{
        "adm2":0.95079,
        "motion2":2.89882,
        "ms_ssim":0.97861,
        "psnr":35.34608,
        "ssim":0.96571,
        "vif_scale0":0.50021,
        "vif_scale1":0.8499100000000001,
        "vif_scale2":0.89879,
        "vif_scale3":0.92427,
        "vmaf":80.29343
      }
    },
    {
      "frameNum":86,
      "metrics":{
        "adm2":0.95368,
        "motion2":2.88812,
        "ms_ssim":0.97866,
        "psnr":35.35623,
        "ssim":0.96605,
        "vif_scale0":0.50175,
        "vif_scale1":0.85021,
        "vif_scale2":0.8985300000000001,
        "vif_scale3":0.92302,
        "vmaf":80.78206
      }
    },
    {
      "frameNum":87,
      "metrics":{
        "adm2":0.9575399999999999,
        "motion2":2.88812,
        "ms_ssim":0.97863,
        "psnr":35.28174,
        "ssim":0.9661,
        "vif_scale0":0.49971,
        "vif_scale1":0.85002,
        "vif_scale2":0.89862,
        "vif_scale3":0.92406,
        "vmaf":81.68295000000001
      }
    },
    {
      "frameNum":88,
      "metrics":{
        "adm2":0.95131,
        "motion2":2.84611,
        "ms_ssim":0.97871,
        "psnr":35.26176,
        "ssim":0.9659799999999999,
        "vif_scale0":0.5009400000000001,
        "vif_scale1":0.85115,
        "vif_scale2":0.89952,
        "vif_scale3":0.92635,
        "vmaf":80.52436
      }
    },
    {
      "frameNum":89,
      "metrics":{
        "adm2":0.95601,
        "motion2":2.83394,
        "ms_ssim":0.97823,
        "psnr":35.18556,
        "ssim":0.96549,
        "vif_scale0":0.49767,
        "vif_scale1":0.84966,
        "vif_scale2":0.8982,
        "vif_scale3":0.92457,
        "vmaf":81.32334
      }
    },
    {
      "frameNum":90,
      "metrics":{
        "adm2":0.95458,
        "motion2":2.74566,
        "ms_ssim":0.97853,
        "psnr":35.2117,
        "ssim":0.96568,
        "vif_scale0":0.50004,
        "vif_scale1":0.85041,
        "vif_scale2":0.89868,
        "vif_scale3":0.92344,
        "vmaf":80.84443
      }
    },
    {
      "frameNum":91,
      "metrics":{
        "adm2":0.95797,
        "motion2":2.74566,
        "ms_ssim":0.97817,
        "psnr":35.18476,
        "ssim":0.96511,
        "vif_scale0":0.49748,
        "vif_scale1":0.84827,
        "vif_scale2":0.89708,
        "vif_scale3":0.92478,
        "vmaf":81.60666000000001
      }
    },
    {
      "frameNum":92,
      "metrics":{
        "adm2":0.95167,
        "motion2":2.76452,
        "ms_ssim":0.97815,
        "psnr":35.19351,
        "ssim":0.96484,
        "vif_scale0":0.49829,
        "vif_scale1":0.84855,
        "vif_scale2":0.89715,
        "vif_scale3":0.92484,
        "vmaf":80.3051
      }
    },
    {
      "frameNum":93,
      "metrics":{
        "adm2":0.95523,
        "motion2":2.77303,
        "ms_ssim":0.97816,
        "psnr":35.23642,
        "ssim":0.96529,
        "vif_scale0":0.49964,
        "vif_scale1":0.84905,
        "vif_scale2":0.89741,
        "vif_scale3":0.9222399999999999,
        "vmaf":80.87554
      }
    },
    {
      "frameNum":94,
      "metrics":{
        "adm2":0.955,
        "motion2":2.72122,
        "ms_ssim":0.9781,
        "psnr":35.23491,
        "ssim":0.96526,
        "vif_scale0":0.49839,
        "vif_scale1":0.85017,
        "vif_scale2":0.89871,
        "vif_scale3":0.9226,
        "vmaf":80.84571
      }
    },
    {
      "frameNum":95,
      "metrics":{
        "adm2":0.9522699999999999,
        "motion2":2.72122,
        "ms_ssim":0.97775,
        "psnr":35.18209,
        "ssim":0.96469,
        "vif_scale0":0.49571,
        "vif_scale1":0.84655,
        "vif_scale2":0.8954800000000001,
        "vif_scale3":0.92254,
        "vmaf":80.14922
      }
    },
    {
      "frameNum":96,
      "metrics":{
        "adm2":0.92515,
        "motion2":2.71322,
        "ms_ssim":0.96275,
        "psnr":34.70391,
        "ssim":0.93194,
        "vif_scale0":0.35294,
        "vif_scale1":0.77739,
        "vif_scale2":0.87747,
        "vif_scale3":0.92608,
        "vmaf":74.68474999999999
      }
    },
    {
      "frameNum":97,
      "metrics":{
        "adm2":0.93584,
        "motion2":2.71322,
        "ms_ssim":0.96773,
        "psnr":35.37548,
        "ssim":0.94157,
        "vif_scale0":0.38602,
        "vif_scale1":0.80564,
        "vif_scale2":0.89508,
        "vif_scale3":0.93866,
        "vmaf":78.29707999999999
      }
    },
    {
      "frameNum":98,
      "metrics":{
        "adm2":0.94607,
        "motion2":2.65905,
        "ms_ssim":0.9734,
        "psnr":36.11636,
        "ssim":0.95125,
        "vif_scale0":0.42073,
        "vif_scale1":0.8365,
        "vif_scale2":0.91413,
        "vif_scale3":0.95135,
        "vmaf":81.91871
      }
    },
    {
      "frameNum":99,
      "metrics":{
        "adm2":0.95045,
        "motion2":2.60271,
        "ms_ssim":0.97707,
        "psnr":36.58569,
        "ssim":0.95807,
        "vif_scale0":0.44506,
        "vif_scale1":0.86066,
        "vif_scale2":0.92843,
        "vif_scale3":0.95839,
        "vmaf":83.81068
      }
    },
    {
      "frameNum":100,
      "metrics":{
        "adm2":0.94992,
        "motion2":2.60271,
        "ms_ssim":0.97794,
        "psnr":36.45396,
        "ssim":0.95982,
        "vif_scale0":0.44883,
        "vif_scale1":0.86111,
        "vif_scale2":0.92717,
        "vif_scale3":0.95743,
        "vmaf":83.56167000000001
      }
    },
    {
      "frameNum":101,
      "metrics":{
        "adm2":0.95347,
        "motion2":2.70609,
        "ms_ssim":0.97981,
        "psnr":36.77632,
        "ssim":0.96315,
        "vif_scale0":0.46627,
        "vif_scale1":0.87112,
        "vif_scale2":0.93276,
        "vif_scale3":0.96165,
        "vmaf":84.94816
      }
    },
    {
      "frameNum":102,
      "metrics":{
        "adm2":0.95578,
        "motion2":2.64312,
        "ms_ssim":0.98085,
        "psnr":36.91217,
        "ssim":0.96493,
        "vif_scale0":0.47573,
        "vif_scale1":0.87747,
        "vif_scale2":0.93562,
        "vif_scale3":0.96301,
        "vmaf":85.56627
      }
    },
    {
      "frameNum":103,
      "metrics":{
        "adm2":0.9574,
        "motion2":2.64312,
        "ms_ssim":0.98188,
        "psnr":37.09283,
        "ssim":0.96661,
        "vif_scale0":0.48551,
        "vif_scale1":0.8821,
        "vif_scale2":0.93671,
        "vif_scale3":0.9616,
        "vmaf":85.82733
      }
    },
    {
      "frameNum":104,
      "metrics":{
        "adm2":0.95975,
        "motion2":2.61408,
        "ms_ssim":0.98286,
        "psnr":37.26639,
        "ssim":0.96861,
        "vif_scale0":0.49538,
        "vif_scale1":0.8873,
        "vif_scale2":0.93924,
        "vif_scale3":0.96302,
        "vmaf":86.48966
      }
    },
    {
      "frameNum":105,
      "metrics":{
        "adm2":0.95545,
        "motion2":2.61408,
        "ms_ssim":0.98147,
        "psnr":36.70779,
        "ssim":0.96628,
        "vif_scale0":0.48208,
        "vif_scale1":0.87871,
        "vif_scale2":0.93464,
        "vif_scale3":0.96032,
        "vmaf":85.19708
      }
    },
    {
      "frameNum":106,
      "metrics":{
        "adm2":0.9585900000000001,
        "motion2":2.5642,
        "ms_ssim":0.98192,
        "psnr":36.78,
        "ssim":0.96701,
        "vif_scale0":0.48744,
        "vif_scale1":0.88003,
        "vif_scale2":0.93498,
        "vif_scale3":0.95966,
        "vmaf":85.75824
      }
    },
    {
      "frameNum":107,
      "metrics":{
        "adm2":0.95848,
        "motion2":2.44063,
        "ms_ssim":0.9819099999999999,
        "psnr":36.69698,
        "ssim":0.96698,
        "vif_scale0":0.48703,
        "vif_scale1":0.88017,
        "vif_scale2":0.93466,
        "vif_scale3":0.95949,
        "vmaf":85.56295
      }
    },
    {
      "frameNum":108,
      "metrics":{
        "adm2":0.95947,
        "motion2":2.44063,
        "ms_ssim":0.98244,
        "psnr":36.84131,
        "ssim":0.96823,
        "vif_scale0":0.49566,
        "vif_scale1":0.8816000000000001,
        "vif_scale2":0.9340000000000001,
        "vif_scale3":0.95913,
        "vmaf":85.70135999999999
      }
    },
    {
      "frameNum":109,
      "metrics":{
        "adm2":0.9607599999999999,
        "motion2":2.55395,
        "ms_ssim":0.98286,
        "psnr":36.90656,
        "ssim":0.9688600000000001,
        "vif_scale0":0.50165,
        "vif_scale1":0.88451,
        "vif_scale2":0.93477,
        "vif_scale3":0.95708,
        "vmaf":85.96951
      }
    },
    {
      "frameNum":110,
      "metrics":{
        "adm2":0.95994,
        "motion2":2.52901,
        "ms_ssim":0.9827900000000001,
        "psnr":36.82665,
        "ssim":0.96851,
        "vif_scale0":0.50084,
        "vif_scale1":0.88362,
        "vif_scale2":0.93345,
        "vif_scale3":0.95634,
        "vmaf":85.65436
      }
    },
    {
      "frameNum":111,
      "metrics":{
        "adm2":0.96021,
        "motion2":2.52848,
        "ms_ssim":0.98309,
        "psnr":36.88596,
        "ssim":0.96939,
        "vif_scale0":0.5059399999999999,
        "vif_scale1":0.88469,
        "vif_scale2":0.93287,
        "vif_scale3":0.95552,
        "vmaf":85.61391999999999
      }
    },
    {
      "frameNum":112,
      "metrics":{
        "adm2":0.9587,
        "motion2":2.45564,
        "ms_ssim":0.98303,
        "psnr":36.89712,
        "ssim":0.9692499999999999,
        "vif_scale0":0.50812,
        "vif_scale1":0.8846000000000001,
        "vif_scale2":0.93232,
        "vif_scale3":0.95472,
        "vmaf":85.11657
      }
    },
    {
      "frameNum":113,
      "metrics":{
        "adm2":0.9588,
        "motion2":2.45342,
        "ms_ssim":0.98304,
        "psnr":36.83656,
        "ssim":0.96922,
        "vif_scale0":0.50746,
        "vif_scale1":0.88623,
        "vif_scale2":0.93349,
        "vif_scale3":0.95507,
        "vmaf":85.21254999999999
      }
    },
    {
      "frameNum":114,
      "metrics":{
        "adm2":0.9605900000000001,
        "motion2":2.45342,
        "ms_ssim":0.98317,
        "psnr":36.86983,
        "ssim":0.96989,
        "vif_scale0":0.51032,
        "vif_scale1":0.88578,
        "vif_scale2":0.93308,
        "vif_scale3":0.95417,
        "vmaf":85.50118000000001
      }
    },
    {
      "frameNum":115,
      "metrics":{
        "adm2":0.9620300000000001,
        "motion2":2.33354,
        "ms_ssim":0.9830100000000001,
        "psnr":36.82287,
        "ssim":0.96931,
        "vif_scale0":0.50975,
        "vif_scale1":0.88536,
        "vif_scale2":0.93213,
        "vif_scale3":0.9528,
        "vmaf":85.51864999999999
      }
    },
    {
      "frameNum":116,
      "metrics":{
        "adm2":0.96161,
        "motion2":2.33354,
        "ms_ssim":0.98288,
        "psnr":36.82004,
        "ssim":0.96948,
        "vif_scale0":0.51005,
        "vif_scale1":0.88498,
        "vif_scale2":0.93207,
        "vif_scale3":0.95316,
        "vmaf":85.45368999999999
      }
    },
    {
      "frameNum":117,
      "metrics":{
        "adm2":0.96148,
        "motion2":2.41785,
        "ms_ssim":0.98302,
        "psnr":36.87752,
        "ssim":0.97001,
        "vif_scale0":0.51342,
        "vif_scale1":0.88539,
        "vif_scale2":0.93202,
        "vif_scale3":0.9527600000000001,
        "vmaf":85.48783
      }
    },
    {
      "frameNum":118,
      "metrics":{
        "adm2":0.96267,
        "motion2":2.42359,
        "ms_ssim":0.98286,
        "psnr":36.82752,
        "ssim":0.96971,
        "vif_scale0":0.51246,
        "vif_scale1":0.88624,
        "vif_scale2":0.9327,
        "vif_scale3":0.95328,
        "vmaf":85.81832
      }
    },
    {
      "frameNum":119,
      "metrics":{
        "adm2":0.96332,
        "motion2":2.40567,
        "ms_ssim":0.98294,
        "psnr":36.84238,
        "ssim":0.96992,
        "vif_scale0":0.51416,
        "vif_scale1":0.88675,
        "vif_scale2":0.93368,
        "vif_scale3":0.95412,
        "vmaf":86.03874
      }
    },
    {
      "frameNum":120,
      "metrics":{
        "adm2":0.96292,
        "motion2":2.3687,
        "ms_ssim":0.98287,
        "psnr":36.81534,
        "ssim":0.96991,
        "vif_scale0":0.51475,
        "vif_scale1":0.88636,
        "vif_scale2":0.9327800000000001,
        "vif_scale3":0.95362,
        "vmaf":85.83217
      }
    },
    {
      "frameNum":121,
      "metrics":{
        "adm2":0.96193,
        "motion2":2.3687,
        "ms_ssim":0.9825700000000001,
        "psnr":36.76785,
        "ssim":0.96962,
        "vif_scale0":0.51324,
        "vif_scale1":0.88569,
        "vif_scale2":0.93276,
        "vif_scale3":0.95353,
        "vmaf":85.61629000000001
      }
    },
    {
      "frameNum":122,
      "metrics":{
        "adm2":0.9616400000000001,
        "motion2":2.36701,
        "ms_ssim":0.98268,
        "psnr":36.76804,
        "ssim":0.96996,
        "vif_scale0":0.51428,
        "vif_scale1":0.88593,
        "vif_scale2":0.9323399999999999,
        "vif_scale3":0.95341,
        "vmaf":85.52366000000001
      }
    },
    {
      "frameNum":123,
      "metrics":{
        "adm2":0.95988,
        "motion2":2.31431,
        "ms_ssim":0.9826,
        "psnr":36.74648,
        "ssim":0.97004,
        "vif_scale0":0.51439,
        "vif_scale1":0.88568,
        "vif_scale2":0.9317800000000001,
        "vif_scale3":0.95284,
        "vmaf":85.01927999999999
      }
    },
    {
      "frameNum":124,
      "metrics":{
        "adm2":0.95958,
        "motion2":2.25243,
        "ms_ssim":0.9823499999999999,
        "psnr":36.6859,
        "ssim":0.96974,
        "vif_scale0":0.51119,
        "vif_scale1":0.88509,
        "vif_scale2":0.93094,
        "vif_scale3":0.9523,
        "vmaf":84.81071
      }
    },
    {
      "frameNum":125,
      "metrics":{
        "adm2":0.96024,
        "motion2":2.24519,
        "ms_ssim":0.9821800000000001,
        "psnr":36.67179,
        "ssim":0.96966,
        "vif_scale0":0.51233,
        "vif_scale1":0.8831599999999999,
        "vif_scale2":0.92953,
        "vif_scale3":0.95241,
        "vmaf":84.88829
      }
    },
    {
      "frameNum":126,
      "metrics":{
        "adm2":0.96132,
        "motion2":2.24519,
        "ms_ssim":0.98205,
        "psnr":36.6536,
        "ssim":0.96972,
        "vif_scale0":0.51215,
        "vif_scale1":0.883,
        "vif_scale2":0.92918,
        "vif_scale3":0.95101,
        "vmaf":84.99512
      }
    },
    {
      "frameNum":127,
      "metrics":{
        "adm2":0.96207,
        "motion2":2.25427,
        "ms_ssim":0.98207,
        "psnr":36.63055,
        "ssim":0.96987,
        "vif_scale0":0.51246,
        "vif_scale1":0.88213,
        "vif_scale2":0.92775,
        "vif_scale3":0.94995,
        "vmaf":85.02375000000001
      }
    },
    {
      "frameNum":128,
      "metrics":{
        "adm2":0.96126,
        "motion2":2.20752,
        "ms_ssim":0.9819600000000001,
        "psnr":36.63353,
        "ssim":0.9696900000000001,
        "vif_scale0":0.5133,
        "vif_scale1":0.88225,
        "vif_scale2":0.92826,
        "vif_scale3":0.95023,
        "vmaf":84.83743
      }
    },
    {
      "frameNum":129,
      "metrics":{
        "adm2":0.96211,
        "motion2":2.20752,
        "ms_ssim":0.98201,
        "psnr":36.65424,
        "ssim":0.96984,
        "vif_scale0":0.5154,
        "vif_scale1":0.88374,
        "vif_scale2":0.92924,
        "vif_scale3":0.9510999999999999,
        "vmaf":85.12178
      }
    },
    {
      "frameNum":130,
      "metrics":{
        "adm2":0.96025,
        "motion2":2.16994,
        "ms_ssim":0.98201,
        "psnr":36.64559,
        "ssim":0.96982,
        "vif_scale0":0.51468,
        "vif_scale1":0.8829900000000001,
        "vif_scale2":0.92866,
        "vif_scale3":0.95133,
        "vmaf":84.67641
      }
    },
    {
      "frameNum":131,
      "metrics":{
        "adm2":0.95825,
        "motion2":2.16994,
        "ms_ssim":0.98182,
        "psnr":36.5912,
        "ssim":0.9697,
        "vif_scale0":0.51348,
        "vif_scale1":0.88215,
        "vif_scale2":0.92787,
        "vif_scale3":0.95051,
        "vmaf":84.15797999999999
      }
    },
    {
      "frameNum":132,
      "metrics":{
        "adm2":0.95801,
        "motion2":2.12934,
        "ms_ssim":0.98183,
        "psnr":36.63921,
        "ssim":0.96994,
        "vif_scale0":0.516,
        "vif_scale1":0.88197,
        "vif_scale2":0.92702,
        "vif_scale3":0.94853,
        "vmaf":83.86452
      }
    },
    {
      "frameNum":133,
      "metrics":{
        "adm2":0.95941,
        "motion2":2.1032,
        "ms_ssim":0.98158,
        "psnr":36.60537,
        "ssim":0.96978,
        "vif_scale0":0.51447,
        "vif_scale1":0.88178,
        "vif_scale2":0.92655,
        "vif_scale3":0.94756,
        "vmaf":84.03964999999999
      }
    },
    {
      "frameNum":134,
      "metrics":{
        "adm2":0.95779,
        "motion2":2.1032,
        "ms_ssim":0.98058,
        "psnr":36.32584,
        "ssim":0.96795,
        "vif_scale0":0.50371,
        "vif_scale1":0.87323,
        "vif_scale2":0.92028,
        "vif_scale3":0.94278,
        "vmaf":83.09036999999999
      }
    },
    {
      "frameNum":135,
      "metrics":{
        "adm2":0.95892,
        "motion2":2.14717,
        "ms_ssim":0.9805,
        "psnr":36.34686,
        "ssim":0.96805,
        "vif_scale0":0.50578,
        "vif_scale1":0.87253,
        "vif_scale2":0.91957,
        "vif_scale3":0.94321,
        "vmaf":83.3826
      }
    },
    {
      "frameNum":136,
      "metrics":{
        "adm2":0.95786,
        "motion2":2.09012,
        "ms_ssim":0.98039,
        "psnr":36.34572,
        "ssim":0.96785,
        "vif_scale0":0.50539,
        "vif_scale1":0.8727,
        "vif_scale2":0.91973,
        "vif_scale3":0.94277,
        "vmaf":83.06298
      }
    },
    {
      "frameNum":137,
      "metrics":{
        "adm2":0.95474,
        "motion2":2.05108,
        "ms_ssim":0.97843,
        "psnr":35.80112,
        "ssim":0.96471,
        "vif_scale0":0.48558,
        "vif_scale1":0.86129,
        "vif_scale2":0.91312,
        "vif_scale3":0.93843,
        "vmaf":81.80492
      }
    },
    {
      "frameNum":138,
      "metrics":{
        "adm2":0.95567,
        "motion2":2.05108,
        "ms_ssim":0.97811,
        "psnr":35.78985,
        "ssim":0.96473,
        "vif_scale0":0.48581,
        "vif_scale1":0.8597900000000001,
        "vif_scale2":0.91162,
        "vif_scale3":0.93654,
        "vmaf":81.79810999999999
      }
    },
    {
      "frameNum":139,
      "metrics":{
        "adm2":0.95357,
        "motion2":1.9734,
        "ms_ssim":0.97801,
        "psnr":35.75337,
        "ssim":0.96433,
        "vif_scale0":0.48495,
        "vif_scale1":0.85914,
        "vif_scale2":0.9115799999999999,
        "vif_scale3":0.9369499999999999,
        "vmaf":81.29422
      }
    },
    {
      "frameNum":140,
      "metrics":{
        "adm2":0.9546,
        "motion2":1.9734,
        "ms_ssim":0.97819,
        "psnr":35.71857,
        "ssim":0.96452,
        "vif_scale0":0.4849,
        "vif_scale1":0.85919,
        "vif_scale2":0.91137,
        "vif_scale3":0.93538,
        "vmaf":81.38455
      }
    },
    {
      "frameNum":141,
      "metrics":{
        "adm2":0.95402,
        "motion2":2.00886,
        "ms_ssim":0.97784,
        "psnr":35.65444,
        "ssim":0.96462,
        "vif_scale0":0.4843,
        "vif_scale1":0.85829,
        "vif_scale2":0.9106300000000001,
        "vif_scale3":0.93445,
        "vmaf":81.20441
      }
    },
    {
      "frameNum":142,
      "metrics":{
        "adm2":0.95148,
        "motion2":1.90816,
        "ms_ssim":0.9777400000000001,
        "psnr":35.62617,
        "ssim":0.96388,
        "vif_scale0":0.48223,
        "vif_scale1":0.85668,
        "vif_scale2":0.90837,
        "vif_scale3":0.93175,
        "vmaf":80.25955999999999
      }
    },
    {
      "frameNum":143,
      "metrics":{
        "adm2":0.95203,
        "motion2":1.90816,
        "ms_ssim":0.97763,
        "psnr":35.65276,
        "ssim":0.96375,
        "vif_scale0":0.48362,
        "vif_scale1":0.85577,
        "vif_scale2":0.90763,
        "vif_scale3":0.93127,
        "vmaf":80.30707
      }
    },
    {
      "frameNum":144,
      "metrics":{
        "adm2":0.9533,
        "motion2":1.99136,
        "ms_ssim":0.9775,
        "psnr":35.67666,
        "ssim":0.96373,
        "vif_scale0":0.48465,
        "vif_scale1":0.8557,
        "vif_scale2":0.90705,
        "vif_scale3":0.9320000000000001,
        "vmaf":80.7033
      }
    },
    {
      "frameNum":145,
      "metrics":{
        "adm2":0.95237,
        "motion2":1.93495,
        "ms_ssim":0.97726,
        "psnr":35.62962,
        "ssim":0.9637,
        "vif_scale0":0.48339,
        "vif_scale1":0.85531,
        "vif_scale2":0.90624,
        "vif_scale3":0.9312,
        "vmaf":80.34966
      }
    },
    {
      "frameNum":146,
      "metrics":{
        "adm2":0.95301,
        "motion2":1.93495,
        "ms_ssim":0.97718,
        "psnr":35.63563,
        "ssim":0.96331,
        "vif_scale0":0.48316,
        "vif_scale1":0.8545700000000001,
        "vif_scale2":0.9059700000000001,
        "vif_scale3":0.92979,
        "vmaf":80.36821999999999
      }
    },
    {
      "frameNum":147,
      "metrics":{
        "adm2":0.95525,
        "motion2":1.95818,
        "ms_ssim":0.97717,
        "psnr":35.64027,
        "ssim":0.96334,
        "vif_scale0":0.48299,
        "vif_scale1":0.85442,
        "vif_scale2":0.90516,
        "vif_scale3":0.92684,
        "vmaf":80.60899999999999
      }
    },
    {
      "frameNum":148,
      "metrics":{
        "adm2":0.95573,
        "motion2":1.9012,
        "ms_ssim":0.97704,
        "psnr":35.65452,
        "ssim":0.9634200000000001,
        "vif_scale0":0.48355,
        "vif_scale1":0.85451,
        "vif_scale2":0.90518,
        "vif_scale3":0.92766,
        "vmaf":80.70688
      }
    },
    {
      "frameNum":149,
      "metrics":{
        "adm2":0.95604,
        "motion2":1.88815,
        "ms_ssim":0.97671,
        "psnr":35.63909,
        "ssim":0.9632500000000001,
        "vif_scale0":0.48235,
        "vif_scale1":0.85385,
        "vif_scale2":0.90426,
        "vif_scale3":0.92626,
        "vmaf":80.61698
      }
    },
    {
      "frameNum":150,
      "metrics":{
        "adm2":0.95518,
        "motion2":1.88815,
        "ms_ssim":0.97679,
        "psnr":35.64521,
        "ssim":0.96318,
        "vif_scale0":0.4837,
        "vif_scale1":0.8539099999999999,
        "vif_scale2":0.90422,
        "vif_scale3":0.92638,
        "vmaf":80.43783000000001
      }
    },
    {
      "frameNum":151,
      "metrics":{
        "adm2":0.95629,
        "motion2":1.83007,
        "ms_ssim":0.97673,
        "psnr":35.62884,
        "ssim":0.96323,
        "vif_scale0":0.48382,
        "vif_scale1":0.85316,
        "vif_scale2":0.90332,
        "vif_scale3":0.9263,
        "vmaf":80.56185000000001
      }
    },
    {
      "frameNum":152,
      "metrics":{
        "adm2":0.95631,
        "motion2":1.83007,
        "ms_ssim":0.97659,
        "psnr":35.62452,
        "ssim":0.96331,
        "vif_scale0":0.48285,
        "vif_scale1":0.85324,
        "vif_scale2":0.9025,
        "vif_scale3":0.92498,
        "vmaf":80.43562
      }
    },
    {
      "frameNum":153,
      "metrics":{
        "adm2":0.95477,
        "motion2":1.85573,
        "ms_ssim":0.97657,
        "psnr":35.65436,
        "ssim":0.96346,
        "vif_scale0":0.48591,
        "vif_scale1":0.85262,
        "vif_scale2":0.90196,
        "vif_scale3":0.92402,
        "vmaf":80.04159
      }
    },
    {
      "frameNum":154,
      "metrics":{
        "adm2":0.95687,
        "motion2":1.89822,
        "ms_ssim":0.9763500000000001,
        "psnr":35.61187,
        "ssim":0.96317,
        "vif_scale0":0.48456,
        "vif_scale1":0.85305,
        "vif_scale2":0.90202,
        "vif_scale3":0.92362,
        "vmaf":80.50767
      }
    },
    {
      "frameNum":155,
      "metrics":{
        "adm2":0.95655,
        "motion2":1.88728,
        "ms_ssim":0.97634,
        "psnr":35.60954,
        "ssim":0.96319,
        "vif_scale0":0.48514,
        "vif_scale1":0.8529,
        "vif_scale2":0.90205,
        "vif_scale3":0.92378,
        "vmaf":80.44092999999999
      }
    },
    {
      "frameNum":156,
      "metrics":{
        "adm2":0.95456,
        "motion2":1.86295,
        "ms_ssim":0.97624,
        "psnr":35.61791,
        "ssim":0.96314,
        "vif_scale0":0.48465,
        "vif_scale1":0.85232,
        "vif_scale2":0.90091,
        "vif_scale3":0.92263,
        "vmaf":79.86069999999999
      }
    },
    {
      "frameNum":157,
      "metrics":{
        "adm2":0.9556,
        "motion2":1.81092,
        "ms_ssim":0.97631,
        "psnr":35.61867,
        "ssim":0.96326,
        "vif_scale0":0.48446,
        "vif_scale1":0.85338,
        "vif_scale2":0.90188,
        "vif_scale3":0.92356,
        "vmaf":80.12728
      }
    },
    {
      "frameNum":158,
      "metrics":{
        "adm2":0.95473,
        "motion2":1.81092,
        "ms_ssim":0.9762,
        "psnr":35.6376,
        "ssim":0.96358,
        "vif_scale0":0.48619,
        "vif_scale1":0.85238,
        "vif_scale2":0.90081,
        "vif_scale3":0.9222900000000001,
        "vmaf":79.80195999999999
      }
    },
    {
      "frameNum":159,
      "metrics":{
        "adm2":0.95441,
        "motion2":1.82101,
        "ms_ssim":0.97639,
        "psnr":35.66865,
        "ssim":0.96377,
        "vif_scale0":0.48726,
        "vif_scale1":0.85458,
        "vif_scale2":0.9020899999999999,
        "vif_scale3":0.92248,
        "vmaf":79.80591
      }
    },
    {
      "frameNum":160,
      "metrics":{
        "adm2":0.95572,
        "motion2":1.76079,
        "ms_ssim":0.97604,
        "psnr":35.61481,
        "ssim":0.96344,
        "vif_scale0":0.48501,
        "vif_scale1":0.85354,
        "vif_scale2":0.90147,
        "vif_scale3":0.92141,
        "vmaf":79.91118
      }
    },
    {
      "frameNum":161,
      "metrics":{
        "adm2":0.95439,
        "motion2":1.67921,
        "ms_ssim":0.97597,
        "psnr":35.58074,
        "ssim":0.9635,
        "vif_scale0":0.48284,
        "vif_scale1":0.85341,
        "vif_scale2":0.90097,
        "vif_scale3":0.92113,
        "vmaf":79.5
      }
    },
    {
      "frameNum":162,
      "metrics":{
        "adm2":0.95251,
        "motion2":1.67921,
        "ms_ssim":0.97589,
        "psnr":35.58421,
        "ssim":0.9631999999999999,
        "vif_scale0":0.48395,
        "vif_scale1":0.85272,
        "vif_scale2":0.90118,
        "vif_scale3":0.92215,
        "vmaf":79.18795
      }
    },
    {
      "frameNum":163,
      "metrics":{
        "adm2":0.95458,
        "motion2":1.71087,
        "ms_ssim":0.97572,
        "psnr":35.58657,
        "ssim":0.96313,
        "vif_scale0":0.48582,
        "vif_scale1":0.85276,
        "vif_scale2":0.8999,
        "vif_scale3":0.9210700000000001,
        "vmaf":79.52357000000001
      }
    },
    {
      "frameNum":164,
      "metrics":{
        "adm2":0.95444,
        "motion2":1.70825,
        "ms_ssim":0.97559,
        "psnr":35.57018,
        "ssim":0.96285,
        "vif_scale0":0.48435,
        "vif_scale1":0.8514,
        "vif_scale2":0.89829,
        "vif_scale3":0.91795,
        "vmaf":79.19674999999999
      }
    },
    {
      "frameNum":165,
      "metrics":{
        "adm2":0.95336,
        "motion2":1.70825,
        "ms_ssim":0.97528,
        "psnr":35.54996,
        "ssim":0.96284,
        "vif_scale0":0.48362,
        "vif_scale1":0.8519099999999999,
        "vif_scale2":0.89881,
        "vif_scale3":0.91696,
        "vmaf":78.9166
      }
    },
    {
      "frameNum":166,
      "metrics":{
        "adm2":0.95289,
        "motion2":1.6789,
        "ms_ssim":0.97549,
        "psnr":35.59288,
        "ssim":0.9628100000000001,
        "vif_scale0":0.48505,
        "vif_scale1":0.8522,
        "vif_scale2":0.89907,
        "vif_scale3":0.91745,
        "vmaf":78.82531
      }
    },
    {
      "frameNum":167,
      "metrics":{
        "adm2":0.9534899999999999,
        "motion2":1.6789,
        "ms_ssim":0.97529,
        "psnr":35.55333,
        "ssim":0.96272,
        "vif_scale0":0.48352,
        "vif_scale1":0.85295,
        "vif_scale2":0.8990899999999999,
        "vif_scale3":0.91815,
        "vmaf":79.00778
      }
    },
    {
      "frameNum":168,
      "metrics":{
        "adm2":0.95363,
        "motion2":1.68106,
        "ms_ssim":0.97541,
        "psnr":35.55745,
        "ssim":0.9626400000000001,
        "vif_scale0":0.48406,
        "vif_scale1":0.85275,
        "vif_scale2":0.89837,
        "vif_scale3":0.91787,
        "vmaf":78.98903
      }
    },
    {
      "frameNum":169,
      "metrics":{
        "adm2":0.9547600000000001,
        "motion2":1.67339,
        "ms_ssim":0.9751,
        "psnr":35.51164,
        "ssim":0.96269,
        "vif_scale0":0.4833,
        "vif_scale1":0.85096,
        "vif_scale2":0.89749,
        "vif_scale3":0.9179,
        "vmaf":79.19045
      }
    },
    {
      "frameNum":170,
      "metrics":{
        "adm2":0.9537099999999999,
        "motion2":1.67339,
        "ms_ssim":0.97529,
        "psnr":35.55324,
        "ssim":0.96306,
        "vif_scale0":0.48414,
        "vif_scale1":0.853,
        "vif_scale2":0.89972,
        "vif_scale3":0.91901,
        "vmaf":79.13736
      }
    },
    {
      "frameNum":171,
      "metrics":{
        "adm2":0.95326,
        "motion2":1.62054,
        "ms_ssim":0.97479,
        "psnr":35.50199,
        "ssim":0.96239,
        "vif_scale0":0.48279,
        "vif_scale1":0.85114,
        "vif_scale2":0.89701,
        "vif_scale3":0.91621,
        "vmaf":78.66661999999999
      }
    },
    {
      "frameNum":172,
      "metrics":{
        "adm2":0.95238,
        "motion2":1.62054,
        "ms_ssim":0.97473,
        "psnr":35.48157,
        "ssim":0.96231,
        "vif_scale0":0.48103,
        "vif_scale1":0.85029,
        "vif_scale2":0.8959,
        "vif_scale3":0.91538,
        "vmaf":78.37967
      }
    },
    {
      "frameNum":173,
      "metrics":{
        "adm2":0.9534,
        "motion2":1.63343,
        "ms_ssim":0.97454,
        "psnr":35.48928,
        "ssim":0.96229,
        "vif_scale0":0.48297,
        "vif_scale1":0.85011,
        "vif_scale2":0.89595,
        "vif_scale3":0.91574,
        "vmaf":78.63328
      }
    },
    {
      "frameNum":174,
      "metrics":{
        "adm2":0.95248,
        "motion2":1.66038,
        "ms_ssim":0.97461,
        "psnr":35.52689,
        "ssim":0.96273,
        "vif_scale0":0.48418,
        "vif_scale1":0.85085,
        "vif_scale2":0.8964299999999999,
        "vif_scale3":0.9167,
        "vmaf":78.56126
      }
    },
    {
      "frameNum":175,
      "metrics":{
        "adm2":0.95298,
        "motion2":1.64483,
        "ms_ssim":0.97468,
        "psnr":35.52851,
        "ssim":0.96254,
        "vif_scale0":0.485,
        "vif_scale1":0.85081,
        "vif_scale2":0.89678,
        "vif_scale3":0.91703,
        "vmaf":78.68368
      }
    },
    {
      "frameNum":176,
      "metrics":{
        "adm2":0.95316,
        "motion2":1.61998,
        "ms_ssim":0.97479,
        "psnr":35.49399,
        "ssim":0.96263,
        "vif_scale0":0.48316,
        "vif_scale1":0.85097,
        "vif_scale2":0.89719,
        "vif_scale3":0.9184099999999999,
        "vmaf":78.81811
      }
    },
    {
      "frameNum":177,
      "metrics":{
        "adm2":0.95198,
        "motion2":1.61998,
        "ms_ssim":0.97468,
        "psnr":35.52024,
        "ssim":0.96275,
        "vif_scale0":0.48375,
        "vif_scale1":0.8505200000000001,
        "vif_scale2":0.89651,
        "vif_scale3":0.91765,
        "vmaf":78.48502999999999
      }
    },
    {
      "frameNum":178,
      "metrics":{
        "adm2":0.95292,
        "motion2":1.61132,
        "ms_ssim":0.97435,
        "psnr":35.49192,
        "ssim":0.96234,
        "vif_scale0":0.48275,
        "vif_scale1":0.85027,
        "vif_scale2":0.89686,
        "vif_scale3":0.91703,
        "vmaf":78.64242
      }
    },
    {
      "frameNum":179,
      "metrics":{
        "adm2":0.9522699999999999,
        "motion2":1.60599,
        "ms_ssim":0.97428,
        "psnr":35.49405,
        "ssim":0.96223,
        "vif_scale0":0.48259,
        "vif_scale1":0.85053,
        "vif_scale2":0.89646,
        "vif_scale3":0.91665,
        "vmaf":78.45350999999999
      }
    },
    {
      "frameNum":180,
      "metrics":{
        "adm2":0.95312,
        "motion2":1.60599,
        "ms_ssim":0.97424,
        "psnr":35.48452,
        "ssim":0.96213,
        "vif_scale0":0.48264,
        "vif_scale1":0.85039,
        "vif_scale2":0.89728,
        "vif_scale3":0.91681,
        "vmaf":78.67663
      }
    },
    {
      "frameNum":181,
      "metrics":{
        "adm2":0.95469,
        "motion2":1.58742,
        "ms_ssim":0.97404,
        "psnr":35.47206,
        "ssim":0.96213,
        "vif_scale0":0.4824,
        "vif_scale1":0.84923,
        "vif_scale2":0.89571,
        "vif_scale3":0.91592,
        "vmaf":78.85791999999999
      }
    },
    {
      "frameNum":182,
      "metrics":{
        "adm2":0.95414,
        "motion2":1.53893,
        "ms_ssim":0.97393,
        "psnr":35.43753,
        "ssim":0.96205,
        "vif_scale0":0.48063,
        "vif_scale1":0.84873,
        "vif_scale2":0.89457,
        "vif_scale3":0.91481,
        "vmaf":78.56254
      }
    },
    {
      "frameNum":183,
      "metrics":{
        "adm2":0.9547099999999999,
        "motion2":1.53893,
        "ms_ssim":0.97389,
        "psnr":35.46397,
        "ssim":0.96205,
        "vif_scale0":0.48175,
        "vif_scale1":0.84824,
        "vif_scale2":0.89374,
        "vif_scale3":0.9136,
        "vmaf":78.55543
      }
    },
    {
      "frameNum":184,
      "metrics":{
        "adm2":0.95399,
        "motion2":1.56028,
        "ms_ssim":0.9739,
        "psnr":35.46763,
        "ssim":0.96216,
        "vif_scale0":0.4825,
        "vif_scale1":0.84992,
        "vif_scale2":0.89505,
        "vif_scale3":0.91428,
        "vmaf":78.52813
      }
    },
    {
      "frameNum":185,
      "metrics":{
        "adm2":0.95486,
        "motion2":1.54176,
        "ms_ssim":0.97382,
        "psnr":35.46057,
        "ssim":0.96205,
        "vif_scale0":0.48115,
        "vif_scale1":0.84949,
        "vif_scale2":0.8951,
        "vif_scale3":0.91497,
        "vmaf":78.74791
      }
    },
    {
      "frameNum":186,
      "metrics":{
        "adm2":0.95426,
        "motion2":1.52726,
        "ms_ssim":0.97381,
        "psnr":35.44169,
        "ssim":0.96186,
        "vif_scale0":0.48073,
        "vif_scale1":0.84943,
        "vif_scale2":0.89449,
        "vif_scale3":0.91413,
        "vmaf":78.51845
      }
    },
    {
      "frameNum":187,
      "metrics":{
        "adm2":0.95324,
        "motion2":1.52477,
        "ms_ssim":0.97377,
        "psnr":35.44782,
        "ssim":0.96191,
        "vif_scale0":0.48191,
        "vif_scale1":0.85038,
        "vif_scale2":0.89464,
        "vif_scale3":0.91368,
        "vmaf":78.26878000000001
      }
    },
    {
      "frameNum":188,
      "metrics":{
        "adm2":0.94783,
        "motion2":1.49696,
        "ms_ssim":0.9726,
        "psnr":35.17573,
        "ssim":0.95987,
        "vif_scale0":0.46853,
        "vif_scale1":0.8413,
        "vif_scale2":0.88917,
        "vif_scale3":0.91009,
        "vmaf":76.66997000000001
      }
    },
    {
      "frameNum":189,
      "metrics":{
        "adm2":0.94852,
        "motion2":1.46012,
        "ms_ssim":0.9725,
        "psnr":35.16538,
        "ssim":0.95997,
        "vif_scale0":0.46779,
        "vif_scale1":0.84093,
        "vif_scale2":0.88898,
        "vif_scale3":0.90957,
        "vmaf":76.72774
      }
    },
    {
      "frameNum":190,
      "metrics":{
        "adm2":0.94801,
        "motion2":1.46012,
        "ms_ssim":0.97235,
        "psnr":35.15376,
        "ssim":0.9598100000000001,
        "vif_scale0":0.46786,
        "vif_scale1":0.84026,
        "vif_scale2":0.888,
        "vif_scale3":0.90823,
        "vmaf":76.48294
      }
    },
    {
      "frameNum":191,
      "metrics":{
        "adm2":0.94912,
        "motion2":1.4824,
        "ms_ssim":0.97222,
        "psnr":35.15733,
        "ssim":0.95967,
        "vif_scale0":0.46825,
        "vif_scale1":0.84034,
        "vif_scale2":0.88797,
        "vif_scale3":0.90742,
        "vmaf":76.67780999999999
      }
    },
    {
      "frameNum":192,
      "metrics":{
        "adm2":0.93477,
        "motion2":1.44054,
        "ms_ssim":0.9720299999999999,
        "psnr":35.6898,
        "ssim":0.94795,
        "vif_scale0":0.38182,
        "vif_scale1":0.82829,
        "vif_scale2":0.91086,
        "vif_scale3":0.94809,
        "vmaf":77.92529
      }
    },
    {
      "frameNum":193,
      "metrics":{
        "adm2":0.94184,
        "motion2":1.44054,
        "ms_ssim":0.97573,
        "psnr":36.28884,
        "ssim":0.95563,
        "vif_scale0":0.41172,
        "vif_scale1":0.84906,
        "vif_scale2":0.92274,
        "vif_scale3":0.9553,
        "vmaf":80.28825000000001
      }
    },
    {
      "frameNum":194,
      "metrics":{
        "adm2":0.9478799999999999,
        "motion2":1.46992,
        "ms_ssim":0.97903,
        "psnr":36.8455,
        "ssim":0.96132,
        "vif_scale0":0.43765,
        "vif_scale1":0.86929,
        "vif_scale2":0.9336100000000001,
        "vif_scale3":0.96124,
        "vmaf":82.39627
      }
    },
    {
      "frameNum":195,
      "metrics":{
        "adm2":0.95292,
        "motion2":1.4746,
        "ms_ssim":0.98124,
        "psnr":37.2443,
        "ssim":0.96527,
        "vif_scale0":0.45742,
        "vif_scale1":0.88281,
        "vif_scale2":0.94117,
        "vif_scale3":0.96556,
        "vmaf":84.05804999999999
      }
    },
    {
      "frameNum":196,
      "metrics":{
        "adm2":0.95619,
        "motion2":1.4492,
        "ms_ssim":0.98278,
        "psnr":37.51574,
        "ssim":0.96823,
        "vif_scale0":0.47178,
        "vif_scale1":0.89346,
        "vif_scale2":0.94673,
        "vif_scale3":0.96754,
        "vmaf":85.07429
      }
    },
    {
      "frameNum":197,
      "metrics":{
        "adm2":0.95757,
        "motion2":1.4492,
        "ms_ssim":0.9841299999999999,
        "psnr":37.83234,
        "ssim":0.97084,
        "vif_scale0":0.48771,
        "vif_scale1":0.90167,
        "vif_scale2":0.95013,
        "vif_scale3":0.96905,
        "vmaf":85.59730999999999
      }
    },
    {
      "frameNum":198,
      "metrics":{
        "adm2":0.95925,
        "motion2":1.43213,
        "ms_ssim":0.98506,
        "psnr":38.04334,
        "ssim":0.97263,
        "vif_scale0":0.49794,
        "vif_scale1":0.90867,
        "vif_scale2":0.95407,
        "vif_scale3":0.97232,
        "vmaf":86.34085
      }
    },
    {
      "frameNum":199,
      "metrics":{
        "adm2":0.96183,
        "motion2":1.41437,
        "ms_ssim":0.98561,
        "psnr":38.15857,
        "ssim":0.97366,
        "vif_scale0":0.50476,
        "vif_scale1":0.91173,
        "vif_scale2":0.95499,
        "vif_scale3":0.97227,
        "vmaf":86.89417
      }
    },
    {
      "frameNum":200,
      "metrics":{
        "adm2":0.96363,
        "motion2":1.41437,
        "ms_ssim":0.9862,
        "psnr":38.29594,
        "ssim":0.9748599999999999,
        "vif_scale0":0.51186,
        "vif_scale1":0.91703,
        "vif_scale2":0.95816,
        "vif_scale3":0.97406,
        "vmaf":87.5463
      }
    },
    {
      "frameNum":201,
      "metrics":{
        "adm2":0.96327,
        "motion2":1.42894,
        "ms_ssim":0.98682,
        "psnr":38.40952,
        "ssim":0.97584,
        "vif_scale0":0.51815,
        "vif_scale1":0.92137,
        "vif_scale2":0.96107,
        "vif_scale3":0.9757,
        "vmaf":87.73529000000001
      }
    },
    {
      "frameNum":202,
      "metrics":{
        "adm2":0.9646,
        "motion2":1.39199,
        "ms_ssim":0.98717,
        "psnr":38.53044,
        "ssim":0.9766,
        "vif_scale0":0.52403,
        "vif_scale1":0.92333,
        "vif_scale2":0.9618100000000001,
        "vif_scale3":0.97573,
        "vmaf":87.99890000000001
      }
    },
    {
      "frameNum":203,
      "metrics":{
        "adm2":0.96528,
        "motion2":1.37389,
        "ms_ssim":0.9874000000000001,
        "psnr":38.55961,
        "ssim":0.9770799999999999,
        "vif_scale0":0.52626,
        "vif_scale1":0.92458,
        "vif_scale2":0.9626400000000001,
        "vif_scale3":0.97659,
        "vmaf":88.22313
      }
    },
    {
      "frameNum":204,
      "metrics":{
        "adm2":0.96582,
        "motion2":1.37389,
        "ms_ssim":0.98787,
        "psnr":38.67547,
        "ssim":0.97793,
        "vif_scale0":0.53246,
        "vif_scale1":0.92799,
        "vif_scale2":0.96435,
        "vif_scale3":0.97866,
        "vmaf":88.57201000000001
      }
    },
    {
      "frameNum":205,
      "metrics":{
        "adm2":0.96698,
        "motion2":1.40463,
        "ms_ssim":0.98816,
        "psnr":38.76695,
        "ssim":0.9785,
        "vif_scale0":0.53635,
        "vif_scale1":0.929,
        "vif_scale2":0.96412,
        "vif_scale3":0.97821,
        "vmaf":88.80555
      }
    },
    {
      "frameNum":206,
      "metrics":{
        "adm2":0.96726,
        "motion2":1.38614,
        "ms_ssim":0.98835,
        "psnr":38.79949,
        "ssim":0.97872,
        "vif_scale0":0.53856,
        "vif_scale1":0.93021,
        "vif_scale2":0.96462,
        "vif_scale3":0.97802,
        "vmaf":88.84741
      }
    },
    {
      "frameNum":207,
      "metrics":{
        "adm2":0.96687,
        "motion2":1.38113,
        "ms_ssim":0.98847,
        "psnr":38.81077,
        "ssim":0.97912,
        "vif_scale0":0.53972,
        "vif_scale1":0.93001,
        "vif_scale2":0.9634200000000001,
        "vif_scale3":0.97686,
        "vmaf":88.61239999999999
      }
    },
    {
      "frameNum":208,
      "metrics":{
        "adm2":0.96632,
        "motion2":1.37167,
        "ms_ssim":0.98864,
        "psnr":38.84485,
        "ssim":0.97954,
        "vif_scale0":0.54171,
        "vif_scale1":0.93169,
        "vif_scale2":0.9652500000000001,
        "vif_scale3":0.97915,
        "vmaf":88.74422
      }
    },
    {
      "frameNum":209,
      "metrics":{
        "adm2":0.96673,
        "motion2":1.34512,
        "ms_ssim":0.98886,
        "psnr":38.88922,
        "ssim":0.97987,
        "vif_scale0":0.54391,
        "vif_scale1":0.93343,
        "vif_scale2":0.96646,
        "vif_scale3":0.97973,
        "vmaf":88.89642000000001
      }
    },
    {
      "frameNum":210,
      "metrics":{
        "adm2":0.96752,
        "motion2":1.34069,
        "ms_ssim":0.9890099999999999,
        "psnr":38.92389,
        "ssim":0.98009,
        "vif_scale0":0.54569,
        "vif_scale1":0.93407,
        "vif_scale2":0.9664199999999999,
        "vif_scale3":0.97958,
        "vmaf":89.04418
      }
    },
    {
      "frameNum":211,
      "metrics":{
        "adm2":0.96721,
        "motion2":1.34069,
        "ms_ssim":0.9892300000000001,
        "psnr":38.99891,
        "ssim":0.98051,
        "vif_scale0":0.54939,
        "vif_scale1":0.9353900000000001,
        "vif_scale2":0.96691,
        "vif_scale3":0.97972,
        "vmaf":89.00806
      }
    },
    {
      "frameNum":212,
      "metrics":{
        "adm2":0.96674,
        "motion2":1.34083,
        "ms_ssim":0.98917,
        "psnr":38.94497,
        "ssim":0.98054,
        "vif_scale0":0.54766,
        "vif_scale1":0.93491,
        "vif_scale2":0.96693,
        "vif_scale3":0.97979,
        "vmaf":88.91543
      }
    },
    {
      "frameNum":213,
      "metrics":{
        "adm2":0.96757,
        "motion2":1.31791,
        "ms_ssim":0.9892,
        "psnr":38.95095,
        "ssim":0.98055,
        "vif_scale0":0.54906,
        "vif_scale1":0.9347,
        "vif_scale2":0.96705,
        "vif_scale3":0.98004,
        "vmaf":89.08761
      }
    },
    {
      "frameNum":214,
      "metrics":{
        "adm2":0.9678600000000001,
        "motion2":1.27983,
        "ms_ssim":0.98926,
        "psnr":38.94425,
        "ssim":0.98066,
        "vif_scale0":0.54835,
        "vif_scale1":0.93545,
        "vif_scale2":0.96751,
        "vif_scale3":0.9807399999999999,
        "vmaf":89.18116000000001
      }
    },
    {
      "frameNum":215,
      "metrics":{
        "adm2":0.96723,
        "motion2":1.27983,
        "ms_ssim":0.98928,
        "psnr":38.97041,
        "ssim":0.98064,
        "vif_scale0":0.55,
        "vif_scale1":0.93458,
        "vif_scale2":0.96683,
        "vif_scale3":0.98034,
        "vmaf":88.97949
      }
    },
    {
      "frameNum":216,
      "metrics":{
        "adm2":0.96701,
        "motion2":1.30224,
        "ms_ssim":0.98937,
        "psnr":38.98369,
        "ssim":0.98092,
        "vif_scale0":0.55081,
        "vif_scale1":0.93451,
        "vif_scale2":0.9659,
        "vif_scale3":0.97887,
        "vmaf":88.80171
      }
    },
    {
      "frameNum":217,
      "metrics":{
        "adm2":0.96645,
        "motion2":1.30224,
        "ms_ssim":0.98941,
        "psnr":39.00828,
        "ssim":0.98098,
        "vif_scale0":0.55214,
        "vif_scale1":0.93465,
        "vif_scale2":0.96569,
        "vif_scale3":0.97807,
        "vmaf":88.60552
      }
    },
    {
      "frameNum":218,
      "metrics":{
        "adm2":0.9673,
        "motion2":1.33,
        "ms_ssim":0.98932,
        "psnr":38.99569,
        "ssim":0.9809600000000001,
        "vif_scale0":0.55152,
        "vif_scale1":0.93379,
        "vif_scale2":0.96506,
        "vif_scale3":0.97765,
        "vmaf":88.76069
      }
    },
    {
      "frameNum":219,
      "metrics":{
        "adm2":0.96663,
        "motion2":1.29034,
        "ms_ssim":0.98932,
        "psnr":38.97489,
        "ssim":0.98103,
        "vif_scale0":0.5512,
        "vif_scale1":0.9353,
        "vif_scale2":0.96611,
        "vif_scale3":0.97887,
        "vmaf":88.71635000000001
      }
    },
    {
      "frameNum":220,
      "metrics":{
        "adm2":0.9673,
        "motion2":1.29034,
        "ms_ssim":0.98929,
        "psnr":38.95009,
        "ssim":0.9809099999999999,
        "vif_scale0":0.55008,
        "vif_scale1":0.93441,
        "vif_scale2":0.96563,
        "vif_scale3":0.97741,
        "vmaf":88.72233
      }
    },
    {
      "frameNum":221,
      "metrics":{
        "adm2":0.96637,
        "motion2":1.2942,
        "ms_ssim":0.98926,
        "psnr":38.96314,
        "ssim":0.98107,
        "vif_scale0":0.55071,
        "vif_scale1":0.93331,
        "vif_scale2":0.96461,
        "vif_scale3":0.97653,
        "vmaf":88.40894
      }
    },
    {
      "frameNum":222,
      "metrics":{
        "adm2":0.9668099999999999,
        "motion2":1.26621,
        "ms_ssim":0.98949,
        "psnr":39.00596,
        "ssim":0.98122,
        "vif_scale0":0.55265,
        "vif_scale1":0.9342,
        "vif_scale2":0.96536,
        "vif_scale3":0.9777,
        "vmaf":88.59358
      }
    },
    {
      "frameNum":223,
      "metrics":{
        "adm2":0.96632,
        "motion2":1.26621,
        "ms_ssim":0.9893999999999999,
        "psnr":38.98332,
        "ssim":0.98109,
        "vif_scale0":0.55153,
        "vif_scale1":0.93528,
        "vif_scale2":0.96622,
        "vif_scale3":0.9779,
        "vmaf":88.54634
      }
    },
    {
      "frameNum":224,
      "metrics":{
        "adm2":0.9634200000000001,
        "motion2":1.27449,
        "ms_ssim":0.98859,
        "psnr":38.5078,
        "ssim":0.97965,
        "vif_scale0":0.53669,
        "vif_scale1":0.92614,
        "vif_scale2":0.96097,
        "vif_scale3":0.97435,
        "vmaf":87.43911
      }
    },
    {
      "frameNum":225,
      "metrics":{
        "adm2":0.96347,
        "motion2":1.24715,
        "ms_ssim":0.98835,
        "psnr":38.4341,
        "ssim":0.97931,
        "vif_scale0":0.53382,
        "vif_scale1":0.92449,
        "vif_scale2":0.96021,
        "vif_scale3":0.97489,
        "vmaf":87.42943
      }
    },
    {
      "frameNum":226,
      "metrics":{
        "adm2":0.96428,
        "motion2":1.24715,
        "ms_ssim":0.98844,
        "psnr":38.47644,
        "ssim":0.97932,
        "vif_scale0":0.53484,
        "vif_scale1":0.9247,
        "vif_scale2":0.96051,
        "vif_scale3":0.9749100000000001,
        "vmaf":87.61481000000001
      }
    },
    {
      "frameNum":227,
      "metrics":{
        "adm2":0.96393,
        "motion2":1.284,
        "ms_ssim":0.98844,
        "psnr":38.49578,
        "ssim":0.97942,
        "vif_scale0":0.53562,
        "vif_scale1":0.92367,
        "vif_scale2":0.9589,
        "vif_scale3":0.97342,
        "vmaf":87.39494999999999
      }
    },
    {
      "frameNum":228,
      "metrics":{
        "adm2":0.96539,
        "motion2":1.30878,
        "ms_ssim":0.9883999999999999,
        "psnr":38.50895,
        "ssim":0.97938,
        "vif_scale0":0.53584,
        "vif_scale1":0.92384,
        "vif_scale2":0.95962,
        "vif_scale3":0.97453,
        "vmaf":87.85429999999999
      }
    },
    {
      "frameNum":229,
      "metrics":{
        "adm2":0.96391,
        "motion2":1.27641,
        "ms_ssim":0.98831,
        "psnr":38.48034,
        "ssim":0.97903,
        "vif_scale0":0.53472,
        "vif_scale1":0.9237300000000001,
        "vif_scale2":0.9593,
        "vif_scale3":0.97442,
        "vmaf":87.47969999999999
      }
    },
    {
      "frameNum":230,
      "metrics":{
        "adm2":0.96451,
        "motion2":1.273,
        "ms_ssim":0.98835,
        "psnr":38.4819,
        "ssim":0.97922,
        "vif_scale0":0.53557,
        "vif_scale1":0.9231200000000001,
        "vif_scale2":0.95833,
        "vif_scale3":0.97281,
        "vmaf":87.43163
      }
    },
    {
      "frameNum":231,
      "metrics":{
        "adm2":0.96573,
        "motion2":1.273,
        "ms_ssim":0.98829,
        "psnr":38.45323,
        "ssim":0.9793500000000001,
        "vif_scale0":0.53484,
        "vif_scale1":0.92328,
        "vif_scale2":0.9587599999999999,
        "vif_scale3":0.97336,
        "vmaf":87.7552
      }
    },
    {
      "frameNum":232,
      "metrics":{
        "adm2":0.96477,
        "motion2":1.24205,
        "ms_ssim":0.98838,
        "psnr":38.51276,
        "ssim":0.97944,
        "vif_scale0":0.53654,
        "vif_scale1":0.9231,
        "vif_scale2":0.95839,
        "vif_scale3":0.97261,
        "vmaf":87.43303
      }
    },
    {
      "frameNum":233,
      "metrics":{
        "adm2":0.96252,
        "motion2":1.23917,
        "ms_ssim":0.98834,
        "psnr":38.47558,
        "ssim":0.97924,
        "vif_scale0":0.53465,
        "vif_scale1":0.92228,
        "vif_scale2":0.95801,
        "vif_scale3":0.97277,
        "vmaf":86.94886
      }
    },
    {
      "frameNum":234,
      "metrics":{
        "adm2":0.9636400000000001,
        "motion2":1.23917,
        "ms_ssim":0.98838,
        "psnr":38.52073,
        "ssim":0.97941,
        "vif_scale0":0.53603,
        "vif_scale1":0.9224599999999999,
        "vif_scale2":0.95795,
        "vif_scale3":0.97244,
        "vmaf":87.15637
      }
    },
    {
      "frameNum":235,
      "metrics":{
        "adm2":0.96411,
        "motion2":1.22559,
        "ms_ssim":0.98829,
        "psnr":38.51707,
        "ssim":0.9792,
        "vif_scale0":0.53673,
        "vif_scale1":0.92161,
        "vif_scale2":0.9573199999999999,
        "vif_scale3":0.9718599999999999,
        "vmaf":87.1658
      }
    },
    {
      "frameNum":236,
      "metrics":{
        "adm2":0.9628,
        "motion2":1.20481,
        "ms_ssim":0.98831,
        "psnr":38.48895,
        "ssim":0.97916,
        "vif_scale0":0.53465,
        "vif_scale1":0.92259,
        "vif_scale2":0.9577,
        "vif_scale3":0.97162,
        "vmaf":86.86166
      }
    },
    {
      "frameNum":237,
      "metrics":{
        "adm2":0.96478,
        "motion2":1.20481,
        "ms_ssim":0.9884500000000001,
        "psnr":38.53531,
        "ssim":0.97925,
        "vif_scale0":0.53754,
        "vif_scale1":0.92173,
        "vif_scale2":0.95691,
        "vif_scale3":0.97127,
        "vmaf":87.21709
      }
    },
    {
      "frameNum":238,
      "metrics":{
        "adm2":0.96417,
        "motion2":1.27006,
        "ms_ssim":0.98834,
        "psnr":38.49366,
        "ssim":0.97942,
        "vif_scale0":0.53576,
        "vif_scale1":0.92228,
        "vif_scale2":0.9577,
        "vif_scale3":0.97202,
        "vmaf":87.26298
      }
    },
    {
      "frameNum":239,
      "metrics":{
        "adm2":0.96394,
        "motion2":1.24595,
        "ms_ssim":0.98834,
        "psnr":38.49123,
        "ssim":0.97922,
        "vif_scale0":0.53643,
        "vif_scale1":0.92303,
        "vif_scale2":0.9581,
        "vif_scale3":0.97226,
        "vmaf":87.22221999999999
      }
    },
    {
      "frameNum":240,
      "metrics":{
        "adm2":0.96334,
        "motion2":1.24595,
        "ms_ssim":0.9881799999999999,
        "psnr":38.4469,
        "ssim":0.97884,
        "vif_scale0":0.53415,
        "vif_scale1":0.92184,
        "vif_scale2":0.95735,
        "vif_scale3":0.97242,
        "vmaf":87.07625
      }
    },
    {
      "frameNum":241,
      "metrics":{
        "adm2":0.96387,
        "motion2":1.26057,
        "ms_ssim":0.9882300000000001,
        "psnr":38.43432,
        "ssim":0.979,
        "vif_scale0":0.53527,
        "vif_scale1":0.92237,
        "vif_scale2":0.95749,
        "vif_scale3":0.97231,
        "vmaf":87.20359999999999
      }
    },
    {
      "frameNum":242,
      "metrics":{
        "adm2":0.9628100000000001,
        "motion2":1.16266,
        "ms_ssim":0.9880100000000001,
        "psnr":38.43664,
        "ssim":0.97902,
        "vif_scale0":0.53437,
        "vif_scale1":0.92103,
        "vif_scale2":0.95681,
        "vif_scale3":0.97119,
        "vmaf":86.73824
      }
    },
    {
      "frameNum":243,
      "metrics":{
        "adm2":0.96267,
        "motion2":0.74678,
        "ms_ssim":0.9877,
        "psnr":38.27292,
        "ssim":0.97824,
        "vif_scale0":0.52728,
        "vif_scale1":0.92001,
        "vif_scale2":0.95625,
        "vif_scale3":0.97141,
        "vmaf":86.2079
      }
    },
    {
      "frameNum":244,
      "metrics":{
        "adm2":0.96309,
        "motion2":0.73821,
        "ms_ssim":0.98806,
        "psnr":38.36747,
        "ssim":0.97872,
        "vif_scale0":0.53047,
        "vif_scale1":0.92219,
        "vif_scale2":0.95802,
        "vif_scale3":0.9736900000000001,
        "vmaf":86.53905
      }
    },
    {
      "frameNum":245,
      "metrics":{
        "adm2":0.96404,
        "motion2":0.71153,
        "ms_ssim":0.9887,
        "psnr":38.59958,
        "ssim":0.97986,
        "vif_scale0":0.53988,
        "vif_scale1":0.9265600000000001,
        "vif_scale2":0.95999,
        "vif_scale3":0.97431,
        "vmaf":86.82971000000001
      }
    },
    {
      "frameNum":246,
      "metrics":{
        "adm2":0.96548,
        "motion2":0.6817800000000001,
        "ms_ssim":0.9891799999999999,
        "psnr":38.77823,
        "ssim":0.98072,
        "vif_scale0":0.54754,
        "vif_scale1":0.9309500000000001,
        "vif_scale2":0.9630300000000001,
        "vif_scale3":0.97632,
        "vmaf":87.38182
      }
    },
    {
      "frameNum":247,
      "metrics":{
        "adm2":0.96548,
        "motion2":0.6817800000000001,
        "ms_ssim":0.98942,
        "psnr":38.85202,
        "ssim":0.9812,
        "vif_scale0":0.55163,
        "vif_scale1":0.9329499999999999,
        "vif_scale2":0.96433,
        "vif_scale3":0.9771300000000001,
        "vmaf":87.49782999999999
      }
    },
    {
      "frameNum":248,
      "metrics":{
        "adm2":0.96552,
        "motion2":0.68014,
        "ms_ssim":0.9897,
        "psnr":38.94621,
        "ssim":0.98161,
        "vif_scale0":0.55619,
        "vif_scale1":0.93463,
        "vif_scale2":0.96574,
        "vif_scale3":0.97922,
        "vmaf":87.72553000000001
      }
    },
    {
      "frameNum":249,
      "metrics":{
        "adm2":0.9664,
        "motion2":0.68014,
        "ms_ssim":0.98976,
        "psnr":38.97359,
        "ssim":0.98173,
        "vif_scale0":0.55846,
        "vif_scale1":0.93593,
        "vif_scale2":0.96682,
        "vif_scale3":0.98012,
        "vmaf":88.03143
      }
    }
  ],
  "VMAF score":84.20792237382241,
  "ExecFps":68.81502703505689,
  "PSNR score":36.97981704408722,
  "SSIM score":0.9701582207679749,
  "MS-SSIM score":0.9821714222957548
}
